double_dabble_semana_9/double_dabble_semana_9.vhd
-- Code your design here
library IEEE;
use IEEE.std_logic_1164.all;
use ieee.numeric_std.all;

entity doubledabble is
port(
	clk: in std_logic;
	binary: in std_logic_vector(7 downto 0);
    reset: in std_logic; --ativo em high
    unidade, dezena, centena: out std_logic_vector(3 downto 0);
    done: out std_logic
);
end entity doubledabble;

architecture behavior of doubledabble is
constant k : unsigned(3 downto 0) := "0101"; -- 5 -> esse poderia ter sido criado como int
constant n : unsigned(3 downto 0) := "0011"; -- 3
type states is (idle, check, add, shift, finish); --estados
signal at_state, nx_state : states; --signals para controlar os estados

begin

process(clk, reset) is
begin
	if(reset = '1') then --ao resetar entra no primeiro estado
    	at_state <= idle;
	elsif(clk'event and clk = '1') then --em borda de subida troca o estado (se este mudar)
    	at_state <= nx_state;
    end if;
end process;

process(at_state, clk) is
variable cont : integer := 8; --variavel para contar os deslocamentos
variable add1, add2, add3 : boolean := false; --para controlar se é necessario fazer adição
variable ans : std_logic_vector(11 downto 0) := (others => '0'); --vetor para os deslocamentos
begin
	case at_state is
    	when idle => --primeiro estado reseta tudo
        	nx_state <= check;
            done <= '0';
            cont := 8;
            add1 := false;
            add2 := false;
            add3 := false;
            ans := (others => '0');
            centena <= (others => 'Z'); --alta impedância
            dezena <= (others => 'Z');
            unidade <= (others => 'Z');
        when check => --segundo estado é o checador
        	if(cont = 0) then --se eu terminei a conversao
            	nx_state <= finish; -- prox estado é o final
            else
              --se nao, na borda de descida, para nao conflitar com a borda de subida do processo anterior
                if(clk'event and clk = '0') then 
                    --report integer'image(to_integer(unsigned(ans(3 downto 0)))) &  " >= " & integer'image(to_integer(k)) & " ?" severity note; --apenas um report
                    --verifico se o numero da casa das centenas é maior ou igual a 5
                    if(to_integer(unsigned(ans(11 downto 8))) >= to_integer(k)) then
                        add1 := true;
                    end if;
                    --verifico se o numero da casa das dezenas é maior ou igual a 5
                    if(to_integer(unsigned(ans(7 downto 4))) >= to_integer(k)) then
                        add2 := true;
                    end if;
                    --verifico se o numero da casa das unidades é maior ou igual a 5
                    if(to_integer(unsigned(ans(3 downto 0))) >= to_integer(k)) then
                        add3 := true;
                    end if;
                    --se algum dos numeros for maior que 5
                    if(add1 or add2 or add3) then
                        nx_state <= add; --o proximo estado é o de adição
                    else
                        nx_state <= shift; --caso contrario, é o de deslocamento
                    end if;
                end if;
            end if;
        when add => --estado de adição
        	--verifico em qual numero (centena, dezena ou unidade) devo fazer a soma
            --faço a soma e imediatamente coloco a variavel em false para evitar nova adição
            if add1 then
                ans(11 downto 8) := std_logic_vector(unsigned(ans(11 downto 8)) + n);
                add1 := false;
            end if;
            if add2 then
                ans(7 downto 4) := std_logic_vector(unsigned(ans(7 downto 4)) + n);
                add2 := false;
            end if;
            if add3 then
           		ans(3 downto 0) := std_logic_vector(unsigned(ans(3 downto 0)) + n);
                add3 := false;
            end if;
            nx_state <= shift; --ao final das somas necessárias o proximo estado é o de deslocamento
        when shift => --estado de deslocamento
        	-- na borda de descida realizo o deslocamento
            if(clk'event and clk = '0') then
            	cont := cont - 1;
                ans(11 downto 1) := ans(10 downto 0);
            	ans(0) := binary(cont);
            	nx_state <= check; --depois de deslocar o proximo estado é o de checagem
            end if;
        when finish => --se cheguei neste estado eu terminei a conversao
            done <= '1'; --ativo o sinal de done
            --os sinais de saida recebem seus respectivos numeros
            centena <= ans(11 downto 8); 
            dezena <= ans(7 downto 4);
            unidade <= ans(3 downto 0);
    end case;
    --report "atual state = " & to_string(at_state) & " cont = " & integer'image(cont) & " " & to_string(ans) severity note; --apenas um report
end process; --fim
end architecture behavior;

double_dabble_semana_9/testbench_semana_9.vhd
-- Code your testbench here
library IEEE;
use IEEE.std_logic_1164.all;

entity testbench is
end entity testbench;

architecture test of testbench is

component doubledabble is
port(
	clk: in std_logic;
	binary: in std_logic_vector(7 downto 0);
    reset: in std_logic; --ativo em high
    unidade, dezena, centena: out std_logic_vector(3 downto 0);
    done: out std_logic
);
end component doubledabble;
type numeros_teste is array(0 to 10) of std_logic_vector(7 downto 0); --11 numeros de teste
signal numbers : numeros_teste := ( 0 => "00010101", -- 21
									1 => "00001111", -- 15
                                    2 => "00000101", -- 5
									3 => "00011011", -- 27
                                    4 => "01110011", -- 115
									5 => "00001001", -- 9
                                    6 => "00101010", -- 42
									7 => "10000001", -- 129
                                    8 => "11111111", -- 255
									9 => "11111110", -- 254 
                                    10 => "00000001" -- 1
                                    );
signal number : std_logic_vector(7 downto 0) := numbers(9);
signal reset, done, clk : std_logic := '0';
signal unit, dez, cent : std_logic_vector(3 downto 0);

begin

dut: doubledabble port map(
	binary => number,
    reset => reset,
    done => done,
    unidade => unit,
    dezena => dez,
    centena => cent,
    clk => clk
);

process is
begin
	for i in 0 to 10 loop
        reset <= '1'; --reseta pra iniciar nova conversao
        wait for 5 ns;
        reset <= '0';
    	number <= numbers(i); --coloca em number o numero a ser convertido
        for j in 0 to 25 loop --ciclos de clock
          clk <= '1';
          wait for 5 ns;
          clk <= '0';
          wait for 5 ns;
    	end loop;
    end loop;
wait;
end process;

end architecture test;

double_dabble_semana_9/semana9.vcd
$date
  Thu Nov  5 15:28:43 2020
$end
$version
  GHDL v0
$end
$timescale
  1 fs
$end
$scope module standard $end
$upscope $end
$scope module std_logic_1164 $end
$upscope $end
$scope module numeric_std $end
$upscope $end
$scope module testbench $end
$comment numbers is not handled $end
$var reg 8 ! number[7:0] $end
$var reg 1 " reset $end
$var reg 1 # done $end
$var reg 1 $ clk $end
$var reg 4 % unit[3:0] $end
$var reg 4 & dez[3:0] $end
$var reg 4 ' cent[3:0] $end
$scope module dut $end
$var reg 1 ( clk $end
$var reg 8 ) binary[7:0] $end
$var reg 1 * reset $end
$var reg 4 + unidade[3:0] $end
$var reg 4 , dezena[3:0] $end
$var reg 4 - centena[3:0] $end
$var reg 1 . done $end
$comment at_state is not handled $end
$comment nx_state is not handled $end
$upscope $end
$upscope $end
$enddefinitions $end
#0
b11111110 !
1"
0#
0$
bZZZZ %
bZZZZ &
bZZZZ '
0(
b11111110 )
1*
bZZZZ +
bZZZZ ,
bZZZZ -
0.
#5000000
b00010101 !
0"
1$
1(
b00010101 )
0*
#10000000
0$
0(
#15000000
1$
1(
#20000000
0$
0(
#25000000
1$
1(
#30000000
0$
0(
#35000000
1$
1(
#40000000
0$
0(
#45000000
1$
1(
#50000000
0$
0(
#55000000
1$
1(
#60000000
0$
0(
#65000000
1$
1(
#70000000
0$
0(
#75000000
1$
1(
#80000000
0$
0(
#85000000
1$
1(
#90000000
0$
0(
#95000000
1$
1(
#100000000
0$
0(
#105000000
1$
1(
#110000000
0$
0(
#115000000
1$
1(
#120000000
0$
0(
#125000000
1$
1(
#130000000
0$
0(
#135000000
1$
1(
#140000000
0$
0(
#145000000
1$
1(
#150000000
0$
0(
#155000000
1$
1(
#160000000
0$
0(
#165000000
1$
1(
#170000000
0$
0(
#175000000
1$
1(
#180000000
0$
0(
#185000000
1#
1$
b0001 %
b0010 &
b0000 '
1(
b0001 +
b0010 ,
b0000 -
1.
#190000000
0$
0(
#195000000
1$
1(
#200000000
0$
0(
#205000000
1$
1(
#210000000
0$
0(
#215000000
1$
1(
#220000000
0$
0(
#225000000
1$
1(
#230000000
0$
0(
#235000000
1$
1(
#240000000
0$
0(
#245000000
1$
1(
#250000000
0$
0(
#255000000
1$
1(
#260000000
0$
0(
#265000000
1"
0#
bZZZZ %
bZZZZ &
bZZZZ '
1*
bZZZZ +
bZZZZ ,
bZZZZ -
0.
#270000000
b00001111 !
0"
1$
1(
b00001111 )
0*
#275000000
0$
0(
#280000000
1$
1(
#285000000
0$
0(
#290000000
1$
1(
#295000000
0$
0(
#300000000
1$
1(
#305000000
0$
0(
#310000000
1$
1(
#315000000
0$
0(
#320000000
1$
1(
#325000000
0$
0(
#330000000
1$
1(
#335000000
0$
0(
#340000000
1$
1(
#345000000
0$
0(
#350000000
1$
1(
#355000000
0$
0(
#360000000
1$
1(
#365000000
0$
0(
#370000000
1$
1(
#375000000
0$
0(
#380000000
1$
1(
#385000000
0$
0(
#390000000
1$
1(
#395000000
0$
0(
#400000000
1$
1(
#405000000
0$
0(
#410000000
1$
1(
#415000000
0$
0(
#420000000
1$
1(
#425000000
0$
0(
#430000000
1$
1(
#435000000
0$
0(
#440000000
1$
1(
#445000000
0$
0(
#450000000
1#
1$
b0101 %
b0001 &
b0000 '
1(
b0101 +
b0001 ,
b0000 -
1.
#455000000
0$
0(
#460000000
1$
1(
#465000000
0$
0(
#470000000
1$
1(
#475000000
0$
0(
#480000000
1$
1(
#485000000
0$
0(
#490000000
1$
1(
#495000000
0$
0(
#500000000
1$
1(
#505000000
0$
0(
#510000000
1$
1(
#515000000
0$
0(
#520000000
1$
1(
#525000000
0$
0(
#530000000
1"
0#
bZZZZ %
bZZZZ &
bZZZZ '
1*
bZZZZ +
bZZZZ ,
bZZZZ -
0.
#535000000
b00000101 !
0"
1$
1(
b00000101 )
0*
#540000000
0$
0(
#545000000
1$
1(
#550000000
0$
0(
#555000000
1$
1(
#560000000
0$
0(
#565000000
1$
1(
#570000000
0$
0(
#575000000
1$
1(
#580000000
0$
0(
#585000000
1$
1(
#590000000
0$
0(
#595000000
1$
1(
#600000000
0$
0(
#605000000
1$
1(
#610000000
0$
0(
#615000000
1$
1(
#620000000
0$
0(
#625000000
1$
1(
#630000000
0$
0(
#635000000
1$
1(
#640000000
0$
0(
#645000000
1$
1(
#650000000
0$
0(
#655000000
1$
1(
#660000000
0$
0(
#665000000
1$
1(
#670000000
0$
0(
#675000000
1$
1(
#680000000
0$
0(
#685000000
1$
1(
#690000000
0$
0(
#695000000
1$
1(
#700000000
0$
0(
#705000000
1#
1$
b0101 %
b0000 &
b0000 '
1(
b0101 +
b0000 ,
b0000 -
1.
#710000000
0$
0(
#715000000
1$
1(
#720000000
0$
0(
#725000000
1$
1(
#730000000
0$
0(
#735000000
1$
1(
#740000000
0$
0(
#745000000
1$
1(
#750000000
0$
0(
#755000000
1$
1(
#760000000
0$
0(
#765000000
1$
1(
#770000000
0$
0(
#775000000
1$
1(
#780000000
0$
0(
#785000000
1$
1(
#790000000
0$
0(
#795000000
1"
0#
bZZZZ %
bZZZZ &
bZZZZ '
1*
bZZZZ +
bZZZZ ,
bZZZZ -
0.
#800000000
b00011011 !
0"
1$
1(
b00011011 )
0*
#805000000
0$
0(
#810000000
1$
1(
#815000000
0$
0(
#820000000
1$
1(
#825000000
0$
0(
#830000000
1$
1(
#835000000
0$
0(
#840000000
1$
1(
#845000000
0$
0(
#850000000
1$
1(
#855000000
0$
0(
#860000000
1$
1(
#865000000
0$
0(
#870000000
1$
1(
#875000000
0$
0(
#880000000
1$
1(
#885000000
0$
0(
#890000000
1$
1(
#895000000
0$
0(
#900000000
1$
1(
#905000000
0$
0(
#910000000
1$
1(
#915000000
0$
0(
#920000000
1$
1(
#925000000
0$
0(
#930000000
1$
1(
#935000000
0$
0(
#940000000
1$
1(
#945000000
0$
0(
#950000000
1$
1(
#955000000
0$
0(
#960000000
1$
1(
#965000000
0$
0(
#970000000
1$
1(
#975000000
0$
0(
#980000000
1#
1$
b0111 %
b0010 &
b0000 '
1(
b0111 +
b0010 ,
b0000 -
1.
#985000000
0$
0(
#990000000
1$
1(
#995000000
0$
0(
#1000000000
1$
1(
#1005000000
0$
0(
#1010000000
1$
1(
#1015000000
0$
0(
#1020000000
1$
1(
#1025000000
0$
0(
#1030000000
1$
1(
#1035000000
0$
0(
#1040000000
1$
1(
#1045000000
0$
0(
#1050000000
1$
1(
#1055000000
0$
0(
#1060000000
1"
0#
bZZZZ %
bZZZZ &
bZZZZ '
1*
bZZZZ +
bZZZZ ,
bZZZZ -
0.
#1065000000
b01110011 !
0"
1$
1(
b01110011 )
0*
#1070000000
0$
0(
#1075000000
1$
1(
#1080000000
0$
0(
#1085000000
1$
1(
#1090000000
0$
0(
#1095000000
1$
1(
#1100000000
0$
0(
#1105000000
1$
1(
#1110000000
0$
0(
#1115000000
1$
1(
#1120000000
0$
0(
#1125000000
1$
1(
#1130000000
0$
0(
#1135000000
1$
1(
#1140000000
0$
0(
#1145000000
1$
1(
#1150000000
0$
0(
#1155000000
1$
1(
#1160000000
0$
0(
#1165000000
1$
1(
#1170000000
0$
0(
#1175000000
1$
1(
#1180000000
0$
0(
#1185000000
1$
1(
#1190000000
0$
0(
#1195000000
1$
1(
#1200000000
0$
0(
#1205000000
1$
1(
#1210000000
0$
0(
#1215000000
1$
1(
#1220000000
0$
0(
#1225000000
1$
1(
#1230000000
0$
0(
#1235000000
1$
1(
#1240000000
0$
0(
#1245000000
1$
1(
#1250000000
0$
0(
#1255000000
1$
1(
#1260000000
0$
0(
#1265000000
1#
1$
b0101 %
b0001 &
b0001 '
1(
b0101 +
b0001 ,
b0001 -
1.
#1270000000
0$
0(
#1275000000
1$
1(
#1280000000
0$
0(
#1285000000
1$
1(
#1290000000
0$
0(
#1295000000
1$
1(
#1300000000
0$
0(
#1305000000
1$
1(
#1310000000
0$
0(
#1315000000
1$
1(
#1320000000
0$
0(
#1325000000
1"
0#
bZZZZ %
bZZZZ &
bZZZZ '
1*
bZZZZ +
bZZZZ ,
bZZZZ -
0.
#1330000000
b00001001 !
0"
1$
1(
b00001001 )
0*
#1335000000
0$
0(
#1340000000
1$
1(
#1345000000
0$
0(
#1350000000
1$
1(
#1355000000
0$
0(
#1360000000
1$
1(
#1365000000
0$
0(
#1370000000
1$
1(
#1375000000
0$
0(
#1380000000
1$
1(
#1385000000
0$
0(
#1390000000
1$
1(
#1395000000
0$
0(
#1400000000
1$
1(
#1405000000
0$
0(
#1410000000
1$
1(
#1415000000
0$
0(
#1420000000
1$
1(
#1425000000
0$
0(
#1430000000
1$
1(
#1435000000
0$
0(
#1440000000
1$
1(
#1445000000
0$
0(
#1450000000
1$
1(
#1455000000
0$
0(
#1460000000
1$
1(
#1465000000
0$
0(
#1470000000
1$
1(
#1475000000
0$
0(
#1480000000
1$
1(
#1485000000
0$
0(
#1490000000
1$
1(
#1495000000
0$
0(
#1500000000
1#
1$
b1001 %
b0000 &
b0000 '
1(
b1001 +
b0000 ,
b0000 -
1.
#1505000000
0$
0(
#1510000000
1$
1(
#1515000000
0$
0(
#1520000000
1$
1(
#1525000000
0$
0(
#1530000000
1$
1(
#1535000000
0$
0(
#1540000000
1$
1(
#1545000000
0$
0(
#1550000000
1$
1(
#1555000000
0$
0(
#1560000000
1$
1(
#1565000000
0$
0(
#1570000000
1$
1(
#1575000000
0$
0(
#1580000000
1$
1(
#1585000000
0$
0(
#1590000000
1"
0#
bZZZZ %
bZZZZ &
bZZZZ '
1*
bZZZZ +
bZZZZ ,
bZZZZ -
0.
#1595000000
b00101010 !
0"
1$
1(
b00101010 )
0*
#1600000000
0$
0(
#1605000000
1$
1(
#1610000000
0$
0(
#1615000000
1$
1(
#1620000000
0$
0(
#1625000000
1$
1(
#1630000000
0$
0(
#1635000000
1$
1(
#1640000000
0$
0(
#1645000000
1$
1(
#1650000000
0$
0(
#1655000000
1$
1(
#1660000000
0$
0(
#1665000000
1$
1(
#1670000000
0$
0(
#1675000000
1$
1(
#1680000000
0$
0(
#1685000000
1$
1(
#1690000000
0$
0(
#1695000000
1$
1(
#1700000000
0$
0(
#1705000000
1$
1(
#1710000000
0$
0(
#1715000000
1$
1(
#1720000000
0$
0(
#1725000000
1$
1(
#1730000000
0$
0(
#1735000000
1$
1(
#1740000000
0$
0(
#1745000000
1$
1(
#1750000000
0$
0(
#1755000000
1$
1(
#1760000000
0$
0(
#1765000000
1$
1(
#1770000000
0$
0(
#1775000000
1#
1$
b0010 %
b0100 &
b0000 '
1(
b0010 +
b0100 ,
b0000 -
1.
#1780000000
0$
0(
#1785000000
1$
1(
#1790000000
0$
0(
#1795000000
1$
1(
#1800000000
0$
0(
#1805000000
1$
1(
#1810000000
0$
0(
#1815000000
1$
1(
#1820000000
0$
0(
#1825000000
1$
1(
#1830000000
0$
0(
#1835000000
1$
1(
#1840000000
0$
0(
#1845000000
1$
1(
#1850000000
0$
0(
#1855000000
1"
0#
bZZZZ %
bZZZZ &
bZZZZ '
1*
bZZZZ +
bZZZZ ,
bZZZZ -
0.
#1860000000
b10000001 !
0"
1$
1(
b10000001 )
0*
#1865000000
0$
0(
#1870000000
1$
1(
#1875000000
0$
0(
#1880000000
1$
1(
#1885000000
0$
0(
#1890000000
1$
1(
#1895000000
0$
0(
#1900000000
1$
1(
#1905000000
0$
0(
#1910000000
1$
1(
#1915000000
0$
0(
#1920000000
1$
1(
#1925000000
0$
0(
#1930000000
1$
1(
#1935000000
0$
0(
#1940000000
1$
1(
#1945000000
0$
0(
#1950000000
1$
1(
#1955000000
0$
0(
#1960000000
1$
1(
#1965000000
0$
0(
#1970000000
1$
1(
#1975000000
0$
0(
#1980000000
1$
1(
#1985000000
0$
0(
#1990000000
1$
1(
#1995000000
0$
0(
#2000000000
1$
1(
#2005000000
0$
0(
#2010000000
1$
1(
#2015000000
0$
0(
#2020000000
1$
1(
#2025000000
0$
0(
#2030000000
1$
1(
#2035000000
0$
0(
#2040000000
1$
1(
#2045000000
0$
0(
#2050000000
1$
1(
#2055000000
0$
0(
#2060000000
1#
1$
b1001 %
b0010 &
b0001 '
1(
b1001 +
b0010 ,
b0001 -
1.
#2065000000
0$
0(
#2070000000
1$
1(
#2075000000
0$
0(
#2080000000
1$
1(
#2085000000
0$
0(
#2090000000
1$
1(
#2095000000
0$
0(
#2100000000
1$
1(
#2105000000
0$
0(
#2110000000
1$
1(
#2115000000
0$
0(
#2120000000
1"
0#
bZZZZ %
bZZZZ &
bZZZZ '
1*
bZZZZ +
bZZZZ ,
bZZZZ -
0.
#2125000000
b11111111 !
0"
1$
1(
b11111111 )
0*
