projeto_sqrt_calculator/sqrt_non_restoring.vhd
library IEEE;
use IEEE.std_logic_1164.all;
use ieee.numeric_std.all;

entity sqrt_calculator is
    generic(
        n: natural := 32
    );
    port(
        a: in std_logic_vector(n - 1 downto 0);
        clk, reset: in std_logic;
        s: out std_logic_vector(n / 2 - 1 downto 0);
        r: out std_logic_vector(n - 1 downto 0)
    );
end entity sqrt_calculator;

architecture procedimento of sqrt_calculator is
    function deslocar_numero(k: std_logic_vector; x, tam: natural) return std_logic_vector is
        variable ans : std_logic_vector(tam - 1 downto 0) := (others => '0');
        begin
            ans(tam - x - 1 downto 0) := k(tam - 1 downto x);
            return ans;
    end function deslocar_numero;
    function deslocar_duas_casas_esq(k1: std_logic_vector) return std_logic_vector is
        variable ans: std_logic_vector(k1'length - 1 downto 0) := (others => '0');
        begin
            ans(k1'length - 1 downto 2) := k1(k1'length - 3 downto 0);
            return ans;
    end function deslocar_duas_casas_esq;
    constant q11 : std_logic_vector(n - 1 downto 0) := "00000000000000000000000000000011";
    constant q01 : std_logic_vector(n - 1 downto 0) := "00000000000000000000000000000001";
    begin
        process(reset, clk) is
            variable resto, resto_deslocado, num_deslocado: std_logic_vector(n - 1 downto 0) := (others => '0');
            variable square_root: std_logic_vector(n / 2 - 1 downto 0) := (others => '0');
            variable i: integer := 15;
            begin
                if(reset = '1') then
                    resto := (others => '0');
                    num_deslocado := (others => '0');
                    square_root := (others => '0');
                    i := 15;
                    r <= (others => 'Z');
                    s <= (others => 'Z');
                else
                    if(i >= 0) then
                        if(clk'event and clk = '1') then
                            if(to_integer(signed(resto)) >= 0) then
                                resto_deslocado := deslocar_duas_casas_esq(resto);
                                num_deslocado := deslocar_numero(a, 2 * i, n) and q11;
                                resto_deslocado := resto_deslocado or num_deslocado;
                                num_deslocado := (others => '0');
                                num_deslocado(n / 2 - 1 downto 0) := deslocar_duas_casas_esq(square_root);
                                num_deslocado := num_deslocado or q01;  
                                resto := std_logic_vector(signed(resto_deslocado) - signed(num_deslocado));
                            else
                                resto_deslocado := deslocar_duas_casas_esq(resto);
                                num_deslocado := deslocar_numero(a, 2 * i, n) and q11;
                                resto_deslocado := resto_deslocado or num_deslocado;
                                num_deslocado := (others => '0');
                                num_deslocado(n / 2 - 1 downto 0) := deslocar_duas_casas_esq(square_root);
                                num_deslocado := num_deslocado or q11;  
                                resto := std_logic_vector(signed(resto_deslocado) + signed(num_deslocado));
                            end if;
                            if(to_integer(signed(resto)) >= 0) then
                                square_root(n / 2 - 1 downto 1) := square_root(n / 2 - 2 downto 0);
                                square_root(0) := '1';
                            else
                                square_root(n / 2 - 1 downto 1) := square_root(n / 2 - 2 downto 0);
                                square_root(0) := '0';
                            end if;
                            i := i - 1;
                        end if;
                    else
                        if(to_integer(signed(resto)) < 0) then
                            num_deslocado := (others => '0');
                            num_deslocado(n / 2 - 1 downto 1) := square_root(n / 2 - 2 downto 0);
                            num_deslocado(0) := '1';
                            resto := std_logic_vector(signed(resto) + signed(num_deslocado));
                        end if;
                        r <= resto;
                        s <= square_root;
                    end if;
                end if;
            end process;
end architecture procedimento;

projeto_sqrt_calculator/testbench_sqrt_non_restoring.vhd
library IEEE;
use IEEE.std_logic_1164.all;

entity testbench is
end entity testbench;

architecture test of testbench is
    component sqrt_calculator is
        generic(
            n: natural := 32
        );
        port(
            a: in std_logic_vector(n - 1 downto 0);
            clk, reset: in std_logic;
            s: out std_logic_vector(n / 2 - 1 downto 0);
            r: out std_logic_vector(n - 1 downto 0)
        );
    end component sqrt_calculator;
    
    constant t : natural := 32;
    signal square_root : std_logic_vector(t / 2 - 1 downto 0) := (others => '0');
    signal resto: std_logic_vector(t - 1 downto 0) := (others => '0');
    signal clk, reset : std_logic := '0';
    type numeros_teste is array(0 to 14) of std_logic_vector(t - 1 downto 0); --15 numeros de teste
    signal numbers : numeros_teste := ( 0 => "00000000000000000000001010011111",
                                        1 => "00000000000000000000001110000100",
                                        2 => "00000000000000000000011001101010",
                                        3 => "00000000000000000000000101101001",
                                        4 => "00000000000000000000000011011101",
                                        5 => "00000000000000000000010000000000",
                                        6 => "00000000000000000000001001111011",
                                        7 => "00000000000000000000001111000001",
                                        8 => "00000000000000000000000100011110",
                                        9 => "00000000000000000000010001000001",
                                        10 => "00000000000000000000011110110010",
                                        11 => "00000000000000000000010001000001",
                                        12 => "00000000000000000000010011001010",
                                        13 => "00000000000000000000000010010000",
                                        14 => "00000000000000000000000100110100"
                                        );
    signal num : std_logic_vector(t - 1 downto 0) := (others => '0');
    begin
        dut: sqrt_calculator port map(
            a => num,
            clk => clk,
            s => square_root,
            r => resto,
            reset => reset
        );
        process is
        begin
        for j in 0 to 14 loop
            reset <= '1';
            wait for 5 ns;
            reset <= '0';
            num <= numbers(j);
            for i in 20 downto 0 loop
                clk <= '1';
                wait for 5 ns;
                clk <= '0';
                wait for 5 ns;
            end loop;
        end loop;
        wait;
        end process;
end architecture test;

projeto_sqrt_calculator/test.vcd
$date
  Wed Dec 16 17:04:47 2020
$end
$version
  GHDL v0
$end
$timescale
  1 fs
$end
$scope module standard $end
$upscope $end
$scope module std_logic_1164 $end
$upscope $end
$scope module numeric_std $end
$upscope $end
$scope module testbench $end
$var reg 16 ! square_root[15:0] $end
$var reg 32 " resto[31:0] $end
$var reg 1 # clk $end
$var reg 1 $ reset $end
$comment numbers is not handled $end
$var reg 32 % num[31:0] $end
$scope module dut $end
$var reg 32 & a[31:0] $end
$var reg 1 ' clk $end
$var reg 1 ( reset $end
$var reg 16 ) s[15:0] $end
$var reg 32 * r[31:0] $end
$upscope $end
$upscope $end
$enddefinitions $end
#0
bZZZZZZZZZZZZZZZZ !
bZZZZZZZZZZZZZZZZZZZZZZZZZZZZZZZZ "
0#
1$
b00000000000000000000000000000000 %
b00000000000000000000000000000000 &
0'
1(
bZZZZZZZZZZZZZZZZ )
bZZZZZZZZZZZZZZZZZZZZZZZZZZZZZZZZ *
#5000000
1#
0$
b00000000000000000000001010011111 %
b00000000000000000000001010011111 &
1'
0(
#10000000
0#
0'
#15000000
1#
1'
#20000000
0#
0'
#25000000
1#
1'
#30000000
0#
0'
#35000000
1#
1'
#40000000
0#
0'
#45000000
1#
1'
#50000000
0#
0'
#55000000
1#
1'
#60000000
0#
0'
#65000000
1#
1'
#70000000
0#
0'
#75000000
1#
1'
#80000000
0#
0'
#85000000
1#
1'
#90000000
0#
0'
#95000000
1#
1'
#100000000
0#
0'
#105000000
1#
1'
#110000000
0#
0'
#115000000
1#
1'
#120000000
0#
0'
#125000000
1#
1'
#130000000
0#
0'
#135000000
1#
1'
#140000000
0#
0'
#145000000
1#
1'
#150000000
0#
0'
#155000000
1#
1'
#160000000
b0000000000011001 !
b00000000000000000000000000101110 "
0#
0'
b0000000000011001 )
b00000000000000000000000000101110 *
#165000000
1#
1'
#170000000
0#
0'
#175000000
1#
1'
#180000000
0#
0'
#185000000
1#
1'
#190000000
0#
0'
#195000000
1#
1'
#200000000
0#
0'
#205000000
1#
1'
#210000000
0#
0'
#215000000
bZZZZZZZZZZZZZZZZ !
bZZZZZZZZZZZZZZZZZZZZZZZZZZZZZZZZ "
1$
1(
bZZZZZZZZZZZZZZZZ )
bZZZZZZZZZZZZZZZZZZZZZZZZZZZZZZZZ *
#220000000
1#
0$
b00000000000000000000001110000100 %
b00000000000000000000001110000100 &
1'
0(
#225000000
0#
0'
#230000000
1#
1'
#235000000
0#
0'
#240000000
1#
1'
#245000000
0#
0'
#250000000
1#
1'
#255000000
0#
0'
#260000000
1#
1'
#265000000
0#
0'
#270000000
1#
1'
#275000000
0#
0'
#280000000
1#
1'
#285000000
0#
0'
#290000000
1#
1'
#295000000
0#
0'
#300000000
1#
1'
#305000000
0#
0'
#310000000
1#
1'
#315000000
0#
0'
#320000000
1#
1'
#325000000
0#
0'
#330000000
1#
1'
#335000000
0#
0'
#340000000
1#
1'
#345000000
0#
0'
#350000000
1#
1'
#355000000
0#
0'
#360000000
1#
1'
#365000000
0#
0'
#370000000
1#
1'
#375000000
b0000000000011110 !
b00000000000000000000000000000000 "
0#
0'
b0000000000011110 )
b00000000000000000000000000000000 *
#380000000
1#
1'
#385000000
0#
0'
#390000000
1#
1'
#395000000
0#
0'
#400000000
1#
1'
#405000000
0#
0'
#410000000
1#
1'
#415000000
0#
0'
#420000000
1#
1'
#425000000
0#
0'
#430000000
bZZZZZZZZZZZZZZZZ !
bZZZZZZZZZZZZZZZZZZZZZZZZZZZZZZZZ "
1$
1(
bZZZZZZZZZZZZZZZZ )
bZZZZZZZZZZZZZZZZZZZZZZZZZZZZZZZZ *
#435000000
1#
0$
b00000000000000000000011001101010 %
b00000000000000000000011001101010 &
1'
0(
#440000000
0#
0'
#445000000
1#
1'
#450000000
0#
0'
#455000000
1#
1'
#460000000
0#
0'
#465000000
1#
1'
#470000000
0#
0'
#475000000
1#
1'
#480000000
0#
0'
#485000000
1#
1'
#490000000
0#
0'
#495000000
1#
1'
#500000000
0#
0'
#505000000
1#
1'
#510000000
0#
0'
#515000000
1#
1'
#520000000
0#
0'
#525000000
1#
1'
#530000000
0#
0'
#535000000
1#
1'
#540000000
0#
0'
#545000000
1#
1'
#550000000
0#
0'
#555000000
1#
1'
#560000000
0#
0'
#565000000
1#
1'
#570000000
0#
0'
#575000000
1#
1'
#580000000
0#
0'
#585000000
1#
1'
#590000000
b0000000000101000 !
b00000000000000000000000000101010 "
0#
0'
b0000000000101000 )
b00000000000000000000000000101010 *
#595000000
1#
1'
#600000000
0#
0'
#605000000
1#
1'
#610000000
0#
0'
#615000000
1#
1'
#620000000
0#
0'
#625000000
1#
1'
#630000000
0#
0'
#635000000
1#
1'
#640000000
0#
0'
#645000000
bZZZZZZZZZZZZZZZZ !
bZZZZZZZZZZZZZZZZZZZZZZZZZZZZZZZZ "
1$
1(
bZZZZZZZZZZZZZZZZ )
bZZZZZZZZZZZZZZZZZZZZZZZZZZZZZZZZ *
#650000000
1#
0$
b00000000000000000000000101101001 %
b00000000000000000000000101101001 &
1'
0(
#655000000
0#
0'
#660000000
1#
1'
#665000000
0#
0'
#670000000
1#
1'
#675000000
0#
0'
#680000000
1#
1'
#685000000
0#
0'
#690000000
1#
1'
#695000000
0#
0'
#700000000
1#
1'
#705000000
0#
0'
#710000000
1#
1'
#715000000
0#
0'
#720000000
1#
1'
#725000000
0#
0'
#730000000
1#
1'
#735000000
0#
0'
#740000000
1#
1'
#745000000
0#
0'
#750000000
1#
1'
#755000000
0#
0'
#760000000
1#
1'
#765000000
0#
0'
#770000000
1#
1'
#775000000
0#
0'
#780000000
1#
1'
#785000000
0#
0'
#790000000
1#
1'
#795000000
0#
0'
#800000000
1#
1'
#805000000
b0000000000010011 !
b00000000000000000000000000000000 "
0#
0'
b0000000000010011 )
b00000000000000000000000000000000 *
#810000000
1#
1'
#815000000
0#
0'
#820000000
1#
1'
#825000000
0#
0'
#830000000
1#
1'
#835000000
0#
0'
#840000000
1#
1'
#845000000
0#
0'
#850000000
1#
1'
#855000000
0#
0'
#860000000
bZZZZZZZZZZZZZZZZ !
bZZZZZZZZZZZZZZZZZZZZZZZZZZZZZZZZ "
1$
1(
bZZZZZZZZZZZZZZZZ )
bZZZZZZZZZZZZZZZZZZZZZZZZZZZZZZZZ *
#865000000
1#
0$
b00000000000000000000000011011101 %
b00000000000000000000000011011101 &
1'
0(
#870000000
0#
0'
#875000000
1#
1'
#880000000
0#
0'
#885000000
1#
1'
#890000000
0#
0'
#895000000
1#
1'
#900000000
0#
0'
#905000000
1#
1'
#910000000
0#
0'
#915000000
1#
1'
#920000000
0#
0'
#925000000
1#
1'
#930000000
0#
0'
#935000000
1#
1'
#940000000
0#
0'
#945000000
1#
1'
#950000000
0#
0'
#955000000
1#
1'
#960000000
0#
0'
#965000000
1#
1'
#970000000
0#
0'
#975000000
1#
1'
#980000000
0#
0'
#985000000
1#
1'
#990000000
0#
0'
#995000000
1#
1'
#1000000000
0#
0'
#1005000000
1#
1'
#1010000000
0#
0'
#1015000000
1#
1'
#1020000000
b0000000000001110 !
b00000000000000000000000000011001 "
0#
0'
b0000000000001110 )
b00000000000000000000000000011001 *
#1025000000
1#
1'
#1030000000
0#
0'
#1035000000
1#
1'
#1040000000
0#
0'
#1045000000
1#
1'
#1050000000
0#
0'
#1055000000
1#
1'
#1060000000
0#
0'
#1065000000
1#
1'
#1070000000
0#
0'
#1075000000
bZZZZZZZZZZZZZZZZ !
bZZZZZZZZZZZZZZZZZZZZZZZZZZZZZZZZ "
1$
1(
bZZZZZZZZZZZZZZZZ )
bZZZZZZZZZZZZZZZZZZZZZZZZZZZZZZZZ *
#1080000000
1#
0$
b00000000000000000000010000000000 %
b00000000000000000000010000000000 &
1'
0(
#1085000000
0#
0'
#1090000000
1#
1'
#1095000000
0#
0'
#1100000000
1#
1'
#1105000000
0#
0'
#1110000000
1#
1'
#1115000000
0#
0'
#1120000000
1#
1'
#1125000000
0#
0'
#1130000000
1#
1'
#1135000000
0#
0'
#1140000000
1#
1'
#1145000000
0#
0'
#1150000000
1#
1'
#1155000000
0#
0'
#1160000000
1#
1'
#1165000000
0#
0'
#1170000000
1#
1'
#1175000000
0#
0'
#1180000000
1#
1'
#1185000000
0#
0'
#1190000000
1#
1'
#1195000000
0#
0'
#1200000000
1#
1'
#1205000000
0#
0'
#1210000000
1#
1'
#1215000000
0#
0'
#1220000000
1#
1'
#1225000000
0#
0'
#1230000000
1#
1'
#1235000000
b0000000000100000 !
b00000000000000000000000000000000 "
0#
0'
b0000000000100000 )
b00000000000000000000000000000000 *
#1240000000
1#
1'
#1245000000
0#
0'
#1250000000
1#
1'
#1255000000
0#
0'
#1260000000
1#
1'
#1265000000
0#
0'
#1270000000
1#
1'
#1275000000
0#
0'
#1280000000
1#
1'
#1285000000
0#
0'
#1290000000
bZZZZZZZZZZZZZZZZ !
bZZZZZZZZZZZZZZZZZZZZZZZZZZZZZZZZ "
1$
1(
bZZZZZZZZZZZZZZZZ )
bZZZZZZZZZZZZZZZZZZZZZZZZZZZZZZZZ *
#1295000000
1#
0$
b00000000000000000000001001111011 %
b00000000000000000000001001111011 &
1'
0(
#1300000000
0#
0'
#1305000000
1#
1'
#1310000000
0#
0'
#1315000000
1#
1'
#1320000000
0#
0'
#1325000000
1#
1'
#1330000000
0#
0'
#1335000000
1#
1'
#1340000000
0#
0'
#1345000000
1#
1'
#1350000000
0#
0'
#1355000000
1#
1'
#1360000000
0#
0'
#1365000000
1#
1'
#1370000000
0#
0'
#1375000000
1#
1'
#1380000000
0#
0'
#1385000000
1#
1'
#1390000000
0#
0'
#1395000000
1#
1'
#1400000000
0#
0'
#1405000000
1#
1'
#1410000000
0#
0'
#1415000000
1#
1'
#1420000000
0#
0'
#1425000000
1#
1'
#1430000000
0#
0'
#1435000000
1#
1'
#1440000000
0#
0'
#1445000000
1#
1'
#1450000000
b0000000000011001 !
b00000000000000000000000000001010 "
0#
0'
b0000000000011001 )
b00000000000000000000000000001010 *
#1455000000
1#
1'
#1460000000
0#
0'
#1465000000
1#
1'
#1470000000
0#
0'
#1475000000
1#
1'
#1480000000
0#
0'
#1485000000
1#
1'
#1490000000
0#
0'
#1495000000
1#
1'
#1500000000
0#
0'
#1505000000
bZZZZZZZZZZZZZZZZ !
bZZZZZZZZZZZZZZZZZZZZZZZZZZZZZZZZ "
1$
1(
bZZZZZZZZZZZZZZZZ )
bZZZZZZZZZZZZZZZZZZZZZZZZZZZZZZZZ *
#1510000000
1#
0$
b00000000000000000000001111000001 %
b00000000000000000000001111000001 &
1'
0(
#1515000000
0#
0'
#1520000000
1#
1'
#1525000000
0#
0'
#1530000000
1#
1'
#1535000000
0#
0'
#1540000000
1#
1'
#1545000000
0#
0'
#1550000000
1#
1'
#1555000000
0#
0'
#1560000000
1#
1'
#1565000000
0#
0'
#1570000000
1#
1'
#1575000000
0#
0'
#1580000000
1#
1'
#1585000000
0#
0'
#1590000000
1#
1'
#1595000000
0#
0'
#1600000000
1#
1'
#1605000000
0#
0'
#1610000000
1#
1'
#1615000000
0#
0'
#1620000000
1#
1'
#1625000000
0#
0'
#1630000000
1#
1'
#1635000000
0#
0'
#1640000000
1#
1'
#1645000000
0#
0'
#1650000000
1#
1'
#1655000000
0#
0'
#1660000000
1#
1'
#1665000000
b0000000000011111 !
b00000000000000000000000000000000 "
0#
0'
b0000000000011111 )
b00000000000000000000000000000000 *
#1670000000
1#
1'
#1675000000
0#
0'
#1680000000
1#
1'
#1685000000
0#
0'
#1690000000
1#
1'
#1695000000
0#
0'
#1700000000
1#
1'
#1705000000
0#
0'
#1710000000
1#
1'
#1715000000
0#
0'
#1720000000
bZZZZZZZZZZZZZZZZ !
bZZZZZZZZZZZZZZZZZZZZZZZZZZZZZZZZ "
1$
1(
bZZZZZZZZZZZZZZZZ )
bZZZZZZZZZZZZZZZZZZZZZZZZZZZZZZZZ *
#1725000000
1#
0$
b00000000000000000000000100011110 %
b00000000000000000000000100011110 &
1'
0(
#1730000000
0#
0'
#1735000000
1#
1'
#1740000000
0#
0'
#1745000000
1#
1'
#1750000000
0#
0'
#1755000000
1#
1'
#1760000000
0#
0'
#1765000000
1#
1'
#1770000000
0#
0'
#1775000000
1#
1'
#1780000000
0#
0'
#1785000000
1#
1'
#1790000000
0#
0'
#1795000000
1#
1'
#1800000000
0#
0'
#1805000000
1#
1'
#1810000000
0#
0'
#1815000000
1#
1'
#1820000000
0#
0'
#1825000000
1#
1'
#1830000000
0#
0'
#1835000000
1#
1'
#1840000000
0#
0'
#1845000000
1#
1'
#1850000000
0#
0'
#1855000000
1#
1'
#1860000000
0#
0'
#1865000000
1#
1'
#1870000000
0#
0'
#1875000000
1#
1'
#1880000000
b0000000000010000 !
b00000000000000000000000000011110 "
0#
0'
b0000000000010000 )
b00000000000000000000000000011110 *
#1885000000
1#
1'
#1890000000
0#
0'
#1895000000
1#
1'
#1900000000
0#
0'
#1905000000
1#
1'
#1910000000
0#
0'
#1915000000
1#
1'
#1920000000
0#
0'
#1925000000
1#
1'
#1930000000
0#
0'
#1935000000
bZZZZZZZZZZZZZZZZ !
bZZZZZZZZZZZZZZZZZZZZZZZZZZZZZZZZ "
1$
1(
bZZZZZZZZZZZZZZZZ )
bZZZZZZZZZZZZZZZZZZZZZZZZZZZZZZZZ *
#1940000000
1#
0$
b00000000000000000000010001000001 %
b00000000000000000000010001000001 &
1'
0(
#1945000000
0#
0'
#1950000000
1#
1'
#1955000000
0#
0'
#1960000000
1#
1'
#1965000000
0#
0'
#1970000000
1#
1'
#1975000000
0#
0'
#1980000000
1#
1'
#1985000000
0#
0'
#1990000000
1#
1'
#1995000000
0#
0'
#2000000000
1#
1'
#2005000000
0#
0'
#2010000000
1#
1'
#2015000000
0#
0'
#2020000000
1#
1'
#2025000000
0#
0'
#2030000000
1#
1'
#2035000000
0#
0'
#2040000000
1#
1'
#2045000000
0#
0'
#2050000000
1#
1'
#2055000000
0#
0'
#2060000000
1#
1'
#2065000000
0#
0'
#2070000000
1#
1'
#2075000000
0#
0'
#2080000000
1#
1'
#2085000000
0#
0'
#2090000000
1#
1'
#2095000000
b0000000000100001 !
b00000000000000000000000000000000 "
0#
0'
b0000000000100001 )
b00000000000000000000000000000000 *
#2100000000
1#
1'
#2105000000
0#
0'
#2110000000
1#
1'
#2115000000
0#
0'
#2120000000
1#
1'
#2125000000
0#
0'
#2130000000
1#
1'
#2135000000
0#
0'
#2140000000
1#
1'
#2145000000
0#
0'
#2150000000
bZZZZZZZZZZZZZZZZ !
bZZZZZZZZZZZZZZZZZZZZZZZZZZZZZZZZ "
1$
1(
bZZZZZZZZZZZZZZZZ )
bZZZZZZZZZZZZZZZZZZZZZZZZZZZZZZZZ *
#2155000000
1#
0$
b00000000000000000000011110110010 %
b00000000000000000000011110110010 &
1'
0(
#2160000000
0#
0'
#2165000000
1#
1'
#2170000000
0#
0'
#2175000000
1#
1'
#2180000000
0#
0'
#2185000000
1#
1'
#2190000000
0#
0'
#2195000000
1#
1'
#2200000000
0#
0'
#2205000000
1#
1'
#2210000000
0#
0'
#2215000000
1#
1'
#2220000000
0#
0'
#2225000000
1#
1'
#2230000000
0#
0'
#2235000000
1#
1'
#2240000000
0#
0'
#2245000000
1#
1'
#2250000000
0#
0'
#2255000000
1#
1'
#2260000000
0#
0'
#2265000000
1#
1'
#2270000000
0#
0'
#2275000000
1#
1'
#2280000000
0#
0'
#2285000000
1#
1'
#2290000000
0#
0'
#2295000000
1#
1'
#2300000000
0#
0'
#2305000000
1#
1'
#2310000000
b0000000000101100 !
b00000000000000000000000000100010 "
0#
0'
b0000000000101100 )
b00000000000000000000000000100010 *
#2315000000
1#
1'
#2320000000
0#
0'
#2325000000
1#
1'
#2330000000
0#
0'
#2335000000
1#
1'
#2340000000
0#
0'
#2345000000
1#
1'
#2350000000
0#
0'
#2355000000
1#
1'
#2360000000
0#
0'
#2365000000
bZZZZZZZZZZZZZZZZ !
bZZZZZZZZZZZZZZZZZZZZZZZZZZZZZZZZ "
1$
1(
bZZZZZZZZZZZZZZZZ )
bZZZZZZZZZZZZZZZZZZZZZZZZZZZZZZZZ *
#2370000000
1#
0$
b00000000000000000000010001000001 %
b00000000000000000000010001000001 &
1'
0(
#2375000000
0#
0'
#2380000000
1#
1'
#2385000000
0#
0'
#2390000000
1#
1'
#2395000000
0#
0'
#2400000000
1#
1'
#2405000000
0#
0'
#2410000000
1#
1'
#2415000000
0#
0'
#2420000000
1#
1'
#2425000000
0#
0'
#2430000000
1#
1'
#2435000000
0#
0'
#2440000000
1#
1'
#2445000000
0#
0'
#2450000000
1#
1'
#2455000000
0#
0'
#2460000000
1#
1'
#2465000000
0#
0'
#2470000000
1#
1'
#2475000000
0#
0'
#2480000000
1#
1'
#2485000000
0#
0'
#2490000000
1#
1'
#2495000000
0#
0'
#2500000000
1#
1'
#2505000000
0#
0'
#2510000000
1#
1'
#2515000000
0#
0'
#2520000000
1#
1'
#2525000000
b0000000000100001 !
b00000000000000000000000000000000 "
0#
0'
b0000000000100001 )
b00000000000000000000000000000000 *
#2530000000
1#
1'
#2535000000
0#
0'
#2540000000
1#
1'
#2545000000
0#
0'
#2550000000
1#
1'
#2555000000
0#
0'
#2560000000
1#
1'
#2565000000
0#
0'
#2570000000
1#
1'
#2575000000
0#
0'
#2580000000
bZZZZZZZZZZZZZZZZ !
bZZZZZZZZZZZZZZZZZZZZZZZZZZZZZZZZ "
1$
1(
bZZZZZZZZZZZZZZZZ )
bZZZZZZZZZZZZZZZZZZZZZZZZZZZZZZZZ *
#2585000000
1#
0$
b00000000000000000000010011001010 %
b00000000000000000000010011001010 &
1'
0(
#2590000000
0#
0'
#2595000000
1#
1'
#2600000000
0#
0'
#2605000000
1#
1'
#2610000000
0#
0'
#2615000000
1#
1'
#2620000000
0#
0'
#2625000000
1#
1'
#2630000000
0#
0'
#2635000000
1#
1'
#2640000000
0#
0'
#2645000000
1#
1'
#2650000000
0#
0'
#2655000000
1#
1'
#2660000000
0#
0'
#2665000000
1#
1'
#2670000000
0#
0'
#2675000000
1#
1'
#2680000000
0#
0'
#2685000000
1#
1'
#2690000000
0#
0'
#2695000000
1#
1'
#2700000000
0#
0'
#2705000000
1#
1'
#2710000000
0#
0'
#2715000000
1#
1'
#2720000000
0#
0'
#2725000000
1#
1'
#2730000000
0#
0'
#2735000000
1#
1'
#2740000000
b0000000000100011 !
b00000000000000000000000000000001 "
0#
0'
b0000000000100011 )
b00000000000000000000000000000001 *
#2745000000
1#
1'
#2750000000
0#
0'
#2755000000
1#
1'
#2760000000
0#
0'
#2765000000
1#
1'
#2770000000
0#
0'
#2775000000
1#
1'
#2780000000
0#
0'
#2785000000
1#
1'
#2790000000
0#
0'
#2795000000
bZZZZZZZZZZZZZZZZ !
bZZZZZZZZZZZZZZZZZZZZZZZZZZZZZZZZ "
1$
1(
bZZZZZZZZZZZZZZZZ )
bZZZZZZZZZZZZZZZZZZZZZZZZZZZZZZZZ *
#2800000000
1#
0$
b00000000000000000000000010010000 %
b00000000000000000000000010010000 &
1'
0(
#2805000000
0#
0'
#2810000000
1#
1'
#2815000000
0#
0'
#2820000000
1#
1'
#2825000000
0#
0'
#2830000000
1#
1'
#2835000000
0#
0'
#2840000000
1#
1'
#2845000000
0#
0'
#2850000000
1#
1'
#2855000000
0#
0'
#2860000000
1#
1'
#2865000000
0#
0'
#2870000000
1#
1'
#2875000000
0#
0'
#2880000000
1#
1'
#2885000000
0#
0'
#2890000000
1#
1'
#2895000000
0#
0'
#2900000000
1#
1'
#2905000000
0#
0'
#2910000000
1#
1'
#2915000000
0#
0'
#2920000000
1#
1'
#2925000000
0#
0'
#2930000000
1#
1'
#2935000000
0#
0'
#2940000000
1#
1'
#2945000000
0#
0'
#2950000000
1#
1'
#2955000000
b0000000000001100 !
b00000000000000000000000000000000 "
0#
0'
b0000000000001100 )
b00000000000000000000000000000000 *
#2960000000
1#
1'
#2965000000
0#
0'
#2970000000
1#
1'
#2975000000
0#
0'
#2980000000
1#
1'
#2985000000
0#
0'
#2990000000
1#
1'
#2995000000
0#
0'
#3000000000
1#
1'
#3005000000
0#
0'
#3010000000
bZZZZZZZZZZZZZZZZ !
bZZZZZZZZZZZZZZZZZZZZZZZZZZZZZZZZ "
1$
1(
bZZZZZZZZZZZZZZZZ )
bZZZZZZZZZZZZZZZZZZZZZZZZZZZZZZZZ *
#3015000000
1#
0$
b00000000000000000000000100110100 %
b00000000000000000000000100110100 &
1'
0(
#3020000000
0#
0'
#3025000000
1#
1'
#3030000000
0#
0'
#3035000000
1#
1'
#3040000000
0#
0'
#3045000000
1#
1'
#3050000000
0#
0'
#3055000000
1#
1'
#3060000000
0#
0'
#3065000000
1#
1'
#3070000000
0#
0'
#3075000000
1#
1'
#3080000000
0#
0'
#3085000000
1#
1'
#3090000000
0#
0'
#3095000000
1#
1'
#3100000000
0#
0'
#3105000000
1#
1'
#3110000000
0#
0'
#3115000000
1#
1'
#3120000000
0#
0'
#3125000000
1#
1'
#3130000000
0#
0'
#3135000000
1#
1'
#3140000000
0#
0'
#3145000000
1#
1'
#3150000000
0#
0'
#3155000000
1#
1'
#3160000000
0#
0'
#3165000000
1#
1'
#3170000000
b0000000000010001 !
b00000000000000000000000000010011 "
0#
0'
b0000000000010001 )
b00000000000000000000000000010011 *
