ps2_semana_11/ps2.vhd
library IEEE;
use IEEE.std_logic_1164.all;
use ieee.numeric_std.all;

entity PS_2_Host is
    port(
        clk: in std_logic;
        data: in std_logic;
        ascii: out std_logic_vector(7 downto 0)
    );
end entity PS_2_Host;

architecture host of PS_2_Host is

function scanCode2ascii(a: std_logic_vector) return std_logic_vector is
    variable converted2ascii: std_logic_vector(7 downto 0) := (others => '0');
    constant k: std_logic_vector(7 downto 0) := a;
    begin
        case k is
            when x"1C" => converted2ascii := x"61"; -- a
            when x"32" => converted2ascii := x"62"; -- b
            when x"21" => converted2ascii := x"63"; -- c
            when x"23" => converted2ascii := x"64"; -- d
            when x"24" => converted2ascii := x"65"; -- e 
            when x"2B" => converted2ascii := x"66"; -- f
            when x"34" => converted2ascii := x"67"; -- g
            when x"33" => converted2ascii := x"68"; -- h
            when x"43" => converted2ascii := x"69"; -- i
            when x"3B" => converted2ascii := x"6A"; -- j
            when x"42" => converted2ascii := x"6B"; -- k 
            when x"4B" => converted2ascii := x"6C"; -- l
            when x"3A" => converted2ascii := x"6D"; -- m
            when others => converted2ascii := x"3F"; --?
        end case;
    return converted2ascii;
end function scanCode2ascii;

constant f0: std_logic_vector(7 downto 0) := x"F0";
signal message : std_logic_vector(7 downto 0);

begin

process(clk, data) is
    variable cont : natural := 0;
    variable convert, s_release : boolean := false;
    begin
        if(s_release = false) then
            ascii <= (others => 'Z');
        end if;
        if(clk'event and clk = '0') then
            cont := cont + 1;
            if(cont > 1 and cont <= 9) then    
                message(6 downto 0) <= message(7 downto 1);
                message(7) <= data;
            end if;
            if(cont = 11) then
                cont := 0;
                if(convert = true) then
                    ascii <= scanCode2ascii(message);
                    s_release := true;
                    convert := false;
                end if;
                if(message = f0) then
                    convert := true;
                end if;
            end if;
        end if;
end process;

end architecture host;

ps2_semana_11/testbench_ps2.vhd
library IEEE;
use IEEE.std_logic_1164.all;
use ieee.numeric_std.all;


entity testbench is
end entity testbench;

architecture test of testbench is

function parity_generator(a: std_logic_vector) return std_logic is
    variable cont: integer := 0;
    constant k: std_logic_vector(7 downto 0) := a;
    begin
    for i in 7 downto 0 loop
        if k(i) = '1' then
            cont := cont + 1;
        end if;
    end loop;
    if (cont rem 2) = 1 then
        return '0';
    else
        return '1';
    end if;
end function parity_generator;

component PS_2_Host is
    port(
        clk: in std_logic;
        data: in std_logic;
        ascii: out std_logic_vector(7 downto 0)
    );
end component PS_2_Host;

signal clk, data, parity : std_logic := '0';
signal ascii : std_logic_vector(7 downto 0) := (others => 'Z');
signal to_send : std_logic_vector(10 downto 0) := (others => '0');
type testes is array(0 to 5) of std_logic_vector(7 downto 0);
constant myCases : testes := (0 => x"1C", --a
                              1 => x"32", --b
                              2 => x"21", --c
                              3 => x"23", --d
                              4 => x"24", --e
                              5 => x"2B"); --f
constant f0 : std_logic_vector(7 downto 0) := x"F0";
constant start_bit : std_logic  := '0';
constant stop_bit : std_logic  := '1';

begin

dut: PS_2_Host port map(
    clk => clk,
    data => data,
    ascii => ascii
);

process is
begin
------------------- Apertando tecla a -----------------
    clk <= '1';
    data <= '1';
    wait for 5 ns;
    parity <= parity_generator(myCases(0));
    to_send <= stop_bit & parity & myCases(0) & start_bit;
    for i in 0 to 10 loop
        clk <= '0';
        data <= to_send(i);
        wait for 5 ns;
        clk <= '1';
        wait for 5 ns;
    end loop;
------------------- Liberando tecla a -----------------
    parity <= parity_generator(f0);
    to_send <= stop_bit & parity & f0 & start_bit;
    for i in 0 to 10 loop
        clk <= '0';
        data <= to_send(i);
        wait for 5 ns;
        clk <= '1';
        wait for 5 ns;
    end loop;
    parity <= parity_generator(myCases(0));
    to_send <= stop_bit & parity & myCases(0) & start_bit;
    for i in 0 to 10 loop
        clk <= '0';
        data <= to_send(i);
        wait for 5 ns;
        clk <= '1';
        wait for 5 ns;
    end loop;
------------------- Apertando tecla b -----------------
    clk <= '1';
    data <= '1';
    wait for 5 ns;
    parity <= parity_generator(myCases(1));
    to_send <= stop_bit & parity & myCases(1) & start_bit;
    for i in 0 to 10 loop
        clk <= '0';
        data <= to_send(i);
        wait for 5 ns;
        clk <= '1';
        wait for 5 ns;
    end loop;
------------------- Apertando tecla c -----------------
    clk <= '1';
    data <= '1';
    wait for 5 ns;
    parity <= parity_generator(myCases(2));
    to_send <= stop_bit & parity & myCases(2) & start_bit;
    for i in 0 to 10 loop
        clk <= '0';
        data <= to_send(i);
        wait for 5 ns;
        clk <= '1';
        wait for 5 ns;
    end loop;
------------------- Liberando tecla b -----------------
    parity <= parity_generator(f0);
    to_send <= stop_bit & parity & f0 & start_bit;
    for i in 0 to 10 loop
        clk <= '0';
        data <= to_send(i);
        wait for 5 ns;
        clk <= '1';
        wait for 5 ns;
    end loop;
    parity <= parity_generator(myCases(1));
    to_send <= stop_bit & parity & myCases(1) & start_bit;
    for i in 0 to 10 loop
        clk <= '0';
        data <= to_send(i);
        wait for 5 ns;
        clk <= '1';
        wait for 5 ns;
    end loop;
------------------- Liberando tecla c -----------------
    parity <= parity_generator(f0);
    to_send <= stop_bit & parity & f0 & start_bit;
    for i in 0 to 10 loop
        clk <= '0';
        data <= to_send(i);
        wait for 5 ns;
        clk <= '1';
        wait for 5 ns;
    end loop;
    parity <= parity_generator(myCases(2));
    to_send <= stop_bit & parity & myCases(2) & start_bit;
    for i in 0 to 10 loop
        clk <= '0';
        data <= to_send(i);
        wait for 5 ns;
        clk <= '1';
        wait for 5 ns;
    end loop;
------------------- Apertando tecla d -----------------
    clk <= '1';
    data <= '1';
    wait for 5 ns;
    parity <= parity_generator(myCases(3));
    to_send <= stop_bit & parity & myCases(3) & start_bit;
    for i in 0 to 10 loop
        clk <= '0';
        data <= to_send(i);
        wait for 5 ns;
        clk <= '1';
        wait for 5 ns;
    end loop;
------------------- Liberando tecla d -----------------
    parity <= parity_generator(f0);
    to_send <= stop_bit & parity & f0 & start_bit;
    for i in 0 to 10 loop
        clk <= '0';
        data <= to_send(i);
        wait for 5 ns;
        clk <= '1';
        wait for 5 ns;
    end loop;
    parity <= parity_generator(myCases(3));
    to_send <= stop_bit & parity & myCases(3) & start_bit;
    for i in 0 to 10 loop
        clk <= '0';
        data <= to_send(i);
        wait for 5 ns;
        clk <= '1';
        wait for 5 ns;
    end loop;
------------------- Apertando tecla e -----------------
    clk <= '1';
    data <= '1';
    wait for 5 ns;
    parity <= parity_generator(myCases(4));
    to_send <= stop_bit & parity & myCases(4) & start_bit;
    for i in 0 to 10 loop
        clk <= '0';
        data <= to_send(i);
        wait for 5 ns;
        clk <= '1';
        wait for 5 ns;
    end loop;
------------------- Apertando tecla f -----------------
    clk <= '1';
    data <= '1';
    wait for 5 ns;
    parity <= parity_generator(myCases(5));
    to_send <= stop_bit & parity & myCases(5) & start_bit;
    for i in 0 to 10 loop
        clk <= '0';
        data <= to_send(i);
        wait for 5 ns;
        clk <= '1';
        wait for 5 ns;
    end loop;
------------------- Liberando tecla f -----------------
    parity <= parity_generator(f0);
    to_send <= stop_bit & parity & f0 & start_bit;
    for i in 0 to 10 loop
        clk <= '0';
        data <= to_send(i);
        wait for 5 ns;
        clk <= '1';
        wait for 5 ns;
    end loop;
    parity <= parity_generator(myCases(5));
    to_send <= stop_bit & parity & myCases(5) & start_bit;
    for i in 0 to 10 loop
        clk <= '0';
        data <= to_send(i);
        wait for 5 ns;
        clk <= '1';
        wait for 5 ns;
    end loop;
------------------- Liberando tecla e -----------------
    parity <= parity_generator(f0);
    to_send <= stop_bit & parity & f0 & start_bit;
    for i in 0 to 10 loop
        clk <= '0';
        data <= to_send(i);
        wait for 5 ns;
        clk <= '1';
        wait for 5 ns;
    end loop;
    parity <= parity_generator(myCases(4));
    to_send <= stop_bit & parity & myCases(4) & start_bit;
    for i in 0 to 10 loop
        clk <= '0';
        data <= to_send(i);
        wait for 5 ns;
        clk <= '1';
        wait for 5 ns;
    end loop;
    for i in 0 to 4 loop
        clk <= '0';
        wait for 5 ns;
        clk <= '1';
        wait for 5 ns;
    end loop;

wait;
end process;

end architecture test;

ps2_semana_11/first.vcd
$date
  Fri Nov 20 17:38:38 2020
$end
$version
  GHDL v0
$end
$timescale
  1 fs
$end
$scope module standard $end
$upscope $end
$scope module std_logic_1164 $end
$upscope $end
$scope module numeric_std $end
$upscope $end
$scope module testbench $end
$var reg 1 ! clk $end
$var reg 1 " data $end
$var reg 1 # parity $end
$var reg 8 $ ascii[7:0] $end
$var reg 11 % to_send[10:0] $end
$scope module dut $end
$var reg 1 & clk $end
$var reg 1 ' data $end
$var reg 8 ( ascii[7:0] $end
$var reg 8 ) message[7:0] $end
$upscope $end
$upscope $end
$enddefinitions $end
#0
1!
1"
0#
bZZZZZZZZ $
b00000000000 %
1&
1'
bZZZZZZZZ (
bUUUUUUUU )
#5000000
0!
0"
b10000111000 %
0&
0'
#10000000
1!
1&
#15000000
0!
0&
b0UUUUUUU )
#20000000
1!
1&
#25000000
0!
0&
b00UUUUUU )
#30000000
1!
1&
#35000000
0!
1"
0&
1'
b100UUUUU )
#40000000
1!
1&
#45000000
0!
0&
b1100UUUU )
#50000000
1!
1&
#55000000
0!
0&
b11100UUU )
#60000000
1!
1&
#65000000
0!
0"
0&
0'
b011100UU )
#70000000
1!
1&
#75000000
0!
0&
b0011100U )
#80000000
1!
1&
#85000000
0!
0&
b00011100 )
#90000000
1!
1&
#95000000
0!
0&
#100000000
1!
1&
#105000000
0!
1"
0&
1'
#110000000
1!
1&
#115000000
0!
0"
1#
b10111100000 %
0&
0'
#120000000
1!
1&
#125000000
0!
0&
b00001110 )
#130000000
1!
1&
#135000000
0!
0&
b00000111 )
#140000000
1!
1&
#145000000
0!
0&
b00000011 )
#150000000
1!
1&
#155000000
0!
0&
b00000001 )
#160000000
1!
1&
#165000000
0!
1"
0&
1'
b10000000 )
#170000000
1!
1&
#175000000
0!
0&
b11000000 )
#180000000
1!
1&
#185000000
0!
0&
b11100000 )
#190000000
1!
1&
#195000000
0!
0&
b11110000 )
#200000000
1!
1&
#205000000
0!
0"
0&
0'
#210000000
1!
1&
#215000000
0!
1"
0&
1'
#220000000
1!
1&
#225000000
0!
0"
0#
b11000111000 %
0&
0'
#230000000
1!
1&
#235000000
0!
0&
b01111000 )
#240000000
1!
1&
#245000000
0!
0&
b00111100 )
#250000000
1!
1&
#255000000
0!
1"
0&
1'
b10011110 )
#260000000
1!
1&
#265000000
0!
0&
b11001111 )
#270000000
1!
1&
#275000000
0!
0&
b11100111 )
#280000000
1!
1&
#285000000
0!
0"
0&
0'
b01110011 )
#290000000
1!
1&
#295000000
0!
0&
b00111001 )
#300000000
1!
1&
#305000000
0!
0&
b00011100 )
#310000000
1!
1&
#315000000
0!
1"
0&
1'
#320000000
1!
1&
#325000000
0!
b01100001 $
0&
b01100001 (
#330000000
1!
1&
#335000000
#340000000
0!
0"
b10001100100 %
0&
0'
#345000000
1!
1&
#350000000
0!
0&
b00001110 )
#355000000
1!
1&
#360000000
0!
1"
0&
1'
b10000111 )
#365000000
1!
1&
#370000000
0!
0"
0&
0'
b01000011 )
#375000000
1!
1&
#380000000
0!
0&
b00100001 )
#385000000
1!
1&
#390000000
0!
1"
0&
1'
b10010000 )
#395000000
1!
1&
#400000000
0!
0&
b11001000 )
#405000000
1!
1&
#410000000
0!
0"
0&
0'
b01100100 )
#415000000
1!
1&
#420000000
0!
0&
b00110010 )
#425000000
1!
1&
#430000000
0!
0&
#435000000
1!
1&
#440000000
0!
1"
0&
1'
#445000000
1!
1&
#450000000
#455000000
0!
0"
1#
b10001000010 %
0&
0'
#460000000
1!
1&
#465000000
0!
1"
0&
1'
b10011001 )
#470000000
1!
1&
#475000000
0!
0"
0&
0'
b01001100 )
#480000000
1!
1&
#485000000
0!
0&
b00100110 )
#490000000
1!
1&
#495000000
0!
0&
b00010011 )
#500000000
1!
1&
#505000000
0!
0&
b00001001 )
#510000000
1!
1&
#515000000
0!
1"
0&
1'
b10000100 )
#520000000
1!
1&
#525000000
0!
0"
0&
0'
b01000010 )
#530000000
1!
1&
#535000000
0!
0&
b00100001 )
#540000000
1!
1&
#545000000
0!
0&
#550000000
1!
1&
#555000000
0!
1"
0&
1'
#560000000
1!
1&
#565000000
0!
0"
b11111100000 %
0&
0'
#570000000
1!
1&
#575000000
0!
0&
b00010000 )
#580000000
1!
1&
#585000000
0!
0&
b00001000 )
#590000000
1!
1&
#595000000
0!
0&
b00000100 )
#600000000
1!
1&
#605000000
0!
0&
b00000010 )
#610000000
1!
1&
#615000000
0!
1"
0&
1'
b10000001 )
#620000000
1!
1&
#625000000
0!
0&
b11000000 )
#630000000
1!
1&
#635000000
0!
0&
b11100000 )
#640000000
1!
1&
#645000000
0!
0&
b11110000 )
#650000000
1!
1&
#655000000
0!
0&
#660000000
1!
1&
#665000000
0!
0&
#670000000
1!
1&
#675000000
0!
0"
0#
b11001100100 %
0&
0'
#680000000
1!
1&
#685000000
0!
0&
b01111000 )
#690000000
1!
1&
#695000000
0!
1"
0&
1'
b10111100 )
#700000000
1!
1&
#705000000
0!
0"
0&
0'
b01011110 )
#710000000
1!
1&
#715000000
0!
0&
b00101111 )
#720000000
1!
1&
#725000000
0!
1"
0&
1'
b10010111 )
#730000000
1!
1&
#735000000
0!
0&
b11001011 )
#740000000
1!
1&
#745000000
0!
0"
0&
0'
b01100101 )
#750000000
1!
1&
#755000000
0!
0&
b00110010 )
#760000000
1!
1&
#765000000
0!
1"
0&
1'
#770000000
1!
1&
#775000000
0!
b01100010 $
0&
b01100010 (
#780000000
1!
1&
#785000000
0!
0"
1#
b10111100000 %
0&
0'
#790000000
1!
1&
#795000000
0!
0&
b00011001 )
#800000000
1!
1&
#805000000
0!
0&
b00001100 )
#810000000
1!
1&
#815000000
0!
0&
b00000110 )
#820000000
1!
1&
#825000000
0!
0&
b00000011 )
#830000000
1!
1&
#835000000
0!
1"
0&
1'
b10000001 )
#840000000
1!
1&
#845000000
0!
0&
b11000000 )
#850000000
1!
1&
#855000000
0!
0&
b11100000 )
#860000000
1!
1&
#865000000
0!
0&
b11110000 )
#870000000
1!
1&
#875000000
0!
0"
0&
0'
#880000000
1!
1&
#885000000
0!
1"
0&
1'
#890000000
1!
1&
#895000000
0!
0"
b11001000010 %
0&
0'
#900000000
1!
1&
#905000000
0!
1"
0&
1'
b11111000 )
#910000000
1!
1&
#915000000
0!
0"
0&
0'
b01111100 )
#920000000
1!
1&
#925000000
0!
0&
b00111110 )
#930000000
1!
1&
#935000000
0!
0&
b00011111 )
#940000000
1!
1&
#945000000
0!
0&
b00001111 )
#950000000
1!
1&
#955000000
0!
1"
0&
1'
b10000111 )
#960000000
1!
1&
#965000000
0!
0"
0&
0'
b01000011 )
#970000000
1!
1&
#975000000
0!
0&
b00100001 )
#980000000
1!
1&
#985000000
0!
1"
0&
1'
#990000000
1!
1&
#995000000
0!
b01100011 $
0&
b01100011 (
#1000000000
1!
1&
#1005000000
#1010000000
0!
0"
0#
b11001000110 %
0&
0'
#1015000000
1!
1&
#1020000000
0!
1"
0&
1'
b10010000 )
#1025000000
1!
1&
#1030000000
0!
0&
b11001000 )
#1035000000
1!
1&
#1040000000
0!
0"
0&
0'
b01100100 )
#1045000000
1!
1&
#1050000000
0!
0&
b00110010 )
#1055000000
1!
1&
#1060000000
0!
0&
b00011001 )
#1065000000
1!
1&
#1070000000
0!
1"
0&
1'
b10001100 )
#1075000000
1!
1&
#1080000000
0!
0"
0&
0'
b01000110 )
#1085000000
1!
1&
#1090000000
0!
0&
b00100011 )
#1095000000
1!
1&
#1100000000
0!
1"
0&
1'
#1105000000
1!
1&
#1110000000
0!
0&
#1115000000
1!
1&
#1120000000
0!
0"
1#
b10111100000 %
0&
0'
#1125000000
1!
1&
#1130000000
0!
0&
b00010001 )
#1135000000
1!
1&
#1140000000
0!
0&
b00001000 )
#1145000000
1!
1&
#1150000000
0!
0&
b00000100 )
#1155000000
1!
1&
#1160000000
0!
0&
b00000010 )
#1165000000
1!
1&
#1170000000
0!
1"
0&
1'
b10000001 )
#1175000000
1!
1&
#1180000000
0!
0&
b11000000 )
#1185000000
1!
1&
#1190000000
0!
0&
b11100000 )
#1195000000
1!
1&
#1200000000
0!
0&
b11110000 )
#1205000000
1!
1&
#1210000000
0!
0"
0&
0'
#1215000000
1!
1&
#1220000000
0!
1"
0&
1'
#1225000000
1!
1&
#1230000000
0!
0"
0#
b11001000110 %
0&
0'
#1235000000
1!
1&
#1240000000
0!
1"
0&
1'
b11111000 )
#1245000000
1!
1&
#1250000000
0!
0&
b11111100 )
#1255000000
1!
1&
#1260000000
0!
0"
0&
0'
b01111110 )
#1265000000
1!
1&
#1270000000
0!
0&
b00111111 )
#1275000000
1!
1&
#1280000000
0!
0&
b00011111 )
#1285000000
1!
1&
#1290000000
0!
1"
0&
1'
b10001111 )
#1295000000
1!
1&
#1300000000
0!
0"
0&
0'
b01000111 )
#1305000000
1!
1&
#1310000000
0!
0&
b00100011 )
#1315000000
1!
1&
#1320000000
0!
1"
0&
1'
#1325000000
1!
1&
#1330000000
0!
b01100100 $
0&
b01100100 (
#1335000000
1!
1&
#1340000000
#1345000000
0!
0"
1#
b10001001000 %
0&
0'
#1350000000
1!
1&
#1355000000
0!
0&
b00010001 )
#1360000000
1!
1&
#1365000000
0!
0&
b00001000 )
#1370000000
1!
1&
#1375000000
0!
1"
0&
1'
b10000100 )
#1380000000
1!
1&
#1385000000
0!
0"
0&
0'
b01000010 )
#1390000000
1!
1&
#1395000000
0!
0&
b00100001 )
#1400000000
1!
1&
#1405000000
0!
1"
0&
1'
b10010000 )
#1410000000
1!
1&
#1415000000
0!
0"
0&
0'
b01001000 )
#1420000000
1!
1&
#1425000000
0!
0&
b00100100 )
#1430000000
1!
1&
#1435000000
0!
0&
#1440000000
1!
1&
#1445000000
0!
1"
0&
1'
#1450000000
1!
1&
#1455000000
#1460000000
0!
0"
b11001010110 %
0&
0'
#1465000000
1!
1&
#1470000000
0!
1"
0&
1'
b10010010 )
#1475000000
1!
1&
#1480000000
0!
0&
b11001001 )
#1485000000
1!
1&
#1490000000
0!
0"
0&
0'
b01100100 )
#1495000000
1!
1&
#1500000000
0!
1"
0&
1'
b10110010 )
#1505000000
1!
1&
#1510000000
0!
0"
0&
0'
b01011001 )
#1515000000
1!
1&
#1520000000
0!
1"
0&
1'
b10101100 )
#1525000000
1!
1&
#1530000000
0!
0"
0&
0'
b01010110 )
#1535000000
1!
1&
#1540000000
0!
0&
b00101011 )
#1545000000
1!
1&
#1550000000
0!
1"
0&
1'
#1555000000
1!
1&
#1560000000
0!
0&
#1565000000
1!
1&
#1570000000
0!
0"
b11111100000 %
0&
0'
#1575000000
1!
1&
#1580000000
0!
0&
b00010101 )
#1585000000
1!
1&
#1590000000
0!
0&
b00001010 )
#1595000000
1!
1&
#1600000000
0!
0&
b00000101 )
#1605000000
1!
1&
#1610000000
0!
0&
b00000010 )
#1615000000
1!
1&
#1620000000
0!
1"
0&
1'
b10000001 )
#1625000000
1!
1&
#1630000000
0!
0&
b11000000 )
#1635000000
1!
1&
#1640000000
0!
0&
b11100000 )
#1645000000
1!
1&
#1650000000
0!
0&
b11110000 )
#1655000000
1!
1&
#1660000000
0!
0&
#1665000000
1!
1&
#1670000000
0!
0&
#1675000000
1!
1&
#1680000000
0!
0"
b11001010110 %
0&
0'
#1685000000
1!
1&
#1690000000
0!
1"
0&
1'
b11111000 )
#1695000000
1!
1&
#1700000000
0!
0&
b11111100 )
#1705000000
1!
1&
#1710000000
0!
0"
0&
0'
b01111110 )
#1715000000
1!
1&
#1720000000
0!
1"
0&
1'
b10111111 )
#1725000000
1!
1&
#1730000000
0!
0"
0&
0'
b01011111 )
#1735000000
1!
1&
#1740000000
0!
1"
0&
1'
b10101111 )
#1745000000
1!
1&
#1750000000
0!
0"
0&
0'
b01010111 )
#1755000000
1!
1&
#1760000000
0!
0&
b00101011 )
#1765000000
1!
1&
#1770000000
0!
1"
0&
1'
#1775000000
1!
1&
#1780000000
0!
b01100110 $
0&
b01100110 (
#1785000000
1!
1&
#1790000000
0!
0"
b11111100000 %
0&
0'
#1795000000
1!
1&
#1800000000
0!
0&
b00010101 )
#1805000000
1!
1&
#1810000000
0!
0&
b00001010 )
#1815000000
1!
1&
#1820000000
0!
0&
b00000101 )
#1825000000
1!
1&
#1830000000
0!
0&
b00000010 )
#1835000000
1!
1&
#1840000000
0!
1"
0&
1'
b10000001 )
#1845000000
1!
1&
#1850000000
0!
0&
b11000000 )
#1855000000
1!
1&
#1860000000
0!
0&
b11100000 )
#1865000000
1!
1&
#1870000000
0!
0&
b11110000 )
#1875000000
1!
1&
#1880000000
0!
0&
#1885000000
1!
1&
#1890000000
0!
0&
#1895000000
1!
1&
#1900000000
0!
0"
b11001001000 %
0&
0'
#1905000000
1!
1&
#1910000000
0!
0&
b01111000 )
#1915000000
1!
1&
#1920000000
0!
0&
b00111100 )
#1925000000
1!
1&
#1930000000
0!
1"
0&
1'
b10011110 )
#1935000000
1!
1&
#1940000000
0!
0"
0&
0'
b01001111 )
#1945000000
1!
1&
#1950000000
0!
0&
b00100111 )
#1955000000
1!
1&
#1960000000
0!
1"
0&
1'
b10010011 )
#1965000000
1!
1&
#1970000000
0!
0"
0&
0'
b01001001 )
#1975000000
1!
1&
#1980000000
0!
0&
b00100100 )
#1985000000
1!
1&
#1990000000
0!
1"
0&
1'
#1995000000
1!
1&
#2000000000
0!
b01100101 $
0&
b01100101 (
#2005000000
1!
1&
#2010000000
0!
0&
#2015000000
1!
1&
#2020000000
0!
0&
b10010010 )
#2025000000
1!
1&
#2030000000
0!
0&
b11001001 )
#2035000000
1!
1&
#2040000000
0!
0&
b11100100 )
#2045000000
1!
1&
#2050000000
0!
0&
b11110010 )
